{"frames": {

"A3PZ/Attack0000":
{
	"frame": {"x":170,"y":1004,"w":59,"h":76},
	"rotated": false,
	"trimmed": true,
	"spriteSourceSize": {"x":121,"y":117,"w":59,"h":76},
	"sourceSize": {"w":300,"h":300},
	"pivot": {"x":0.5,"y":0.5}
},
"A3PZ/Attack0001":
{
	"frame": {"x":246,"y":1081,"w":61,"h":70},
	"rotated": false,
	"trimmed": true,
	"spriteSourceSize": {"x":115,"y":123,"w":61,"h":70},
	"sourceSize": {"w":300,"h":300},
	"pivot": {"x":0.5,"y":0.5}
},
"A3PZ/Attack0002":
{
	"frame": {"x":193,"y":750,"w":62,"h":69},
	"rotated": false,
	"trimmed": true,
	"spriteSourceSize": {"x":113,"y":124,"w":62,"h":69},
	"sourceSize": {"w":300,"h":300},
	"pivot": {"x":0.5,"y":0.5}
},
"A3PZ/Attack0003":
{
	"frame": {"x":181,"y":934,"w":66,"h":69},
	"rotated": false,
	"trimmed": true,
	"spriteSourceSize": {"x":109,"y":124,"w":66,"h":69},
	"sourceSize": {"w":300,"h":300},
	"pivot": {"x":0.5,"y":0.5}
},
"A3PZ/Attack0004":
{
	"frame": {"x":1,"y":1012,"w":107,"h":68},
	"rotated": false,
	"trimmed": true,
	"spriteSourceSize": {"x":122,"y":125,"w":107,"h":68},
	"sourceSize": {"w":300,"h":300},
	"pivot": {"x":0.5,"y":0.5}
},
"A3PZ/Attack0005":
{
	"frame": {"x":100,"y":680,"w":96,"h":69},
	"rotated": false,
	"trimmed": true,
	"spriteSourceSize": {"x":120,"y":124,"w":96,"h":69},
	"sourceSize": {"w":300,"h":300},
	"pivot": {"x":0.5,"y":0.5}
},
"A3PZ/Attack0006":
{
	"frame": {"x":95,"y":750,"w":97,"h":69},
	"rotated": false,
	"trimmed": true,
	"spriteSourceSize": {"x":119,"y":124,"w":97,"h":69},
	"sourceSize": {"w":300,"h":300},
	"pivot": {"x":0.5,"y":0.5}
},
"A3PZ/Attack0007":
{
	"frame": {"x":395,"y":84,"w":89,"h":74},
	"rotated": false,
	"trimmed": true,
	"spriteSourceSize": {"x":119,"y":119,"w":89,"h":74},
	"sourceSize": {"w":300,"h":300},
	"pivot": {"x":0.5,"y":0.5}
},
"A3PZ/Attack0008":
{
	"frame": {"x":101,"y":934,"w":79,"h":69},
	"rotated": false,
	"trimmed": true,
	"spriteSourceSize": {"x":119,"y":124,"w":79,"h":69},
	"sourceSize": {"w":300,"h":300},
	"pivot": {"x":0.5,"y":0.5}
},
"A3PZ/Hit0000":
{
	"frame": {"x":170,"y":1004,"w":59,"h":76},
	"rotated": false,
	"trimmed": true,
	"spriteSourceSize": {"x":123,"y":117,"w":59,"h":76},
	"sourceSize": {"w":300,"h":300},
	"pivot": {"x":0.5,"y":0.5}
},
"A3PZ/Hit0001":
{
	"frame": {"x":168,"y":194,"w":62,"h":69},
	"rotated": false,
	"trimmed": true,
	"spriteSourceSize": {"x":117,"y":124,"w":62,"h":69},
	"sourceSize": {"w":300,"h":300},
	"pivot": {"x":0.5,"y":0.5}
},
"A3PZ/Hit0002":
{
	"frame": {"x":125,"y":459,"w":62,"h":69},
	"rotated": false,
	"trimmed": true,
	"spriteSourceSize": {"x":117,"y":124,"w":62,"h":69},
	"sourceSize": {"w":300,"h":300},
	"pivot": {"x":0.5,"y":0.5}
},
"A3PZ/Idle0000":
{
	"frame": {"x":170,"y":1004,"w":59,"h":76},
	"rotated": false,
	"trimmed": true,
	"spriteSourceSize": {"x":121,"y":117,"w":59,"h":76},
	"sourceSize": {"w":300,"h":300},
	"pivot": {"x":0.5,"y":0.5}
},
"A3PZ/Idle0001":
{
	"frame": {"x":282,"y":266,"w":59,"h":74},
	"rotated": false,
	"trimmed": true,
	"spriteSourceSize": {"x":121,"y":119,"w":59,"h":74},
	"sourceSize": {"w":300,"h":300},
	"pivot": {"x":0.5,"y":0.5}
},
"A3PZ/Idle0002":
{
	"frame": {"x":197,"y":676,"w":59,"h":73},
	"rotated": false,
	"trimmed": true,
	"spriteSourceSize": {"x":121,"y":120,"w":59,"h":73},
	"sourceSize": {"w":300,"h":300},
	"pivot": {"x":0.5,"y":0.5}
},
"A3PZ/Idle0003":
{
	"frame": {"x":342,"y":345,"w":59,"h":73},
	"rotated": false,
	"trimmed": true,
	"spriteSourceSize": {"x":121,"y":120,"w":59,"h":73},
	"sourceSize": {"w":300,"h":300},
	"pivot": {"x":0.5,"y":0.5}
},
"A3PZ/Idle0004":
{
	"frame": {"x":170,"y":1004,"w":59,"h":76},
	"rotated": false,
	"trimmed": true,
	"spriteSourceSize": {"x":121,"y":117,"w":59,"h":76},
	"sourceSize": {"w":300,"h":300},
	"pivot": {"x":0.5,"y":0.5}
},
"A3PZ/Walk0000":
{
	"frame": {"x":342,"y":266,"w":54,"h":78},
	"rotated": false,
	"trimmed": true,
	"spriteSourceSize": {"x":125,"y":115,"w":54,"h":78},
	"sourceSize": {"w":300,"h":300},
	"pivot": {"x":0.5,"y":0.5}
},
"A3PZ/Walk0001":
{
	"frame": {"x":247,"y":530,"w":52,"h":67},
	"rotated": false,
	"trimmed": true,
	"spriteSourceSize": {"x":127,"y":126,"w":52,"h":67},
	"sourceSize": {"w":300,"h":300},
	"pivot": {"x":0.5,"y":0.5}
},
"A3PZ/Walk0002":
{
	"frame": {"x":300,"y":530,"w":52,"h":67},
	"rotated": false,
	"trimmed": true,
	"spriteSourceSize": {"x":127,"y":126,"w":52,"h":67},
	"sourceSize": {"w":300,"h":300},
	"pivot": {"x":0.5,"y":0.5}
},
"A3PZ/Walk0003":
{
	"frame": {"x":319,"y":746,"w":53,"h":67},
	"rotated": false,
	"trimmed": true,
	"spriteSourceSize": {"x":127,"y":126,"w":53,"h":67},
	"sourceSize": {"w":300,"h":300},
	"pivot": {"x":0.5,"y":0.5}
},
"A3PZ/Walk0004":
{
	"frame": {"x":197,"y":1081,"w":48,"h":71},
	"rotated": false,
	"trimmed": true,
	"spriteSourceSize": {"x":127,"y":122,"w":48,"h":71},
	"sourceSize": {"w":300,"h":300},
	"pivot": {"x":0.5,"y":0.5}
},
"A3PZ/Walk0005":
{
	"frame": {"x":188,"y":460,"w":62,"h":69},
	"rotated": false,
	"trimmed": true,
	"spriteSourceSize": {"x":124,"y":124,"w":62,"h":69},
	"sourceSize": {"w":300,"h":300},
	"pivot": {"x":0.5,"y":0.5}
},
"A3PZ/Walk0006":
{
	"frame": {"x":226,"y":107,"w":63,"h":78},
	"rotated": false,
	"trimmed": true,
	"spriteSourceSize": {"x":122,"y":115,"w":63,"h":78},
	"sourceSize": {"w":300,"h":300},
	"pivot": {"x":0.5,"y":0.5}
},
"A3PZ/Walk0007":
{
	"frame": {"x":184,"y":530,"w":62,"h":67},
	"rotated": false,
	"trimmed": true,
	"spriteSourceSize": {"x":123,"y":126,"w":62,"h":67},
	"sourceSize": {"w":300,"h":300},
	"pivot": {"x":0.5,"y":0.5}
},
"A3PZ/Walk0008":
{
	"frame": {"x":256,"y":753,"w":62,"h":67},
	"rotated": false,
	"trimmed": true,
	"spriteSourceSize": {"x":123,"y":126,"w":62,"h":67},
	"sourceSize": {"w":300,"h":300},
	"pivot": {"x":0.5,"y":0.5}
},
"A3PZ/Walk0009":
{
	"frame": {"x":137,"y":1081,"w":59,"h":71},
	"rotated": false,
	"trimmed": true,
	"spriteSourceSize": {"x":124,"y":122,"w":59,"h":71},
	"sourceSize": {"w":300,"h":300},
	"pivot": {"x":0.5,"y":0.5}
},
"A3PZ/Walk0010":
{
	"frame": {"x":251,"y":460,"w":60,"h":69},
	"rotated": false,
	"trimmed": true,
	"spriteSourceSize": {"x":126,"y":124,"w":60,"h":69},
	"sourceSize": {"w":300,"h":300},
	"pivot": {"x":0.5,"y":0.5}
},
"Butterfly/Idle0000":
{
	"frame": {"x":455,"y":388,"w":29,"h":26},
	"rotated": false,
	"trimmed": true,
	"spriteSourceSize": {"x":18,"y":29,"w":29,"h":26},
	"sourceSize": {"w":69,"h":87},
	"pivot": {"x":0.5,"y":0.5}
},
"Butterfly/Idle0001":
{
	"frame": {"x":455,"y":388,"w":29,"h":26},
	"rotated": false,
	"trimmed": true,
	"spriteSourceSize": {"x":18,"y":29,"w":29,"h":26},
	"sourceSize": {"w":69,"h":87},
	"pivot": {"x":0.5,"y":0.5}
},
"Buzzar/Attack0000":
{
	"frame": {"x":205,"y":886,"w":32,"h":44},
	"rotated": false,
	"trimmed": true,
	"spriteSourceSize": {"x":18,"y":20,"w":32,"h":44},
	"sourceSize": {"w":69,"h":87},
	"pivot": {"x":0.5,"y":0.5}
},
"Buzzar/Attack0001":
{
	"frame": {"x":454,"y":955,"w":32,"h":44},
	"rotated": false,
	"trimmed": true,
	"spriteSourceSize": {"x":18,"y":20,"w":32,"h":44},
	"sourceSize": {"w":69,"h":87},
	"pivot": {"x":0.5,"y":0.5}
},
"Buzzar/Enraged0000":
{
	"frame": {"x":384,"y":1004,"w":33,"h":37},
	"rotated": false,
	"trimmed": true,
	"spriteSourceSize": {"x":17,"y":20,"w":33,"h":37},
	"sourceSize": {"w":69,"h":87},
	"pivot": {"x":0.5,"y":0.5}
},
"Buzzar/Enraged0001":
{
	"frame": {"x":418,"y":1005,"w":33,"h":37},
	"rotated": false,
	"trimmed": true,
	"spriteSourceSize": {"x":17,"y":20,"w":33,"h":37},
	"sourceSize": {"w":69,"h":87},
	"pivot": {"x":0.5,"y":0.5}
},
"Buzzar/Enraged0002":
{
	"frame": {"x":370,"y":1075,"w":33,"h":37},
	"rotated": false,
	"trimmed": true,
	"spriteSourceSize": {"x":17,"y":20,"w":33,"h":37},
	"sourceSize": {"w":69,"h":87},
	"pivot": {"x":0.5,"y":0.5}
},
"Buzzar/Enraged0003":
{
	"frame": {"x":409,"y":1043,"w":33,"h":37},
	"rotated": false,
	"trimmed": true,
	"spriteSourceSize": {"x":17,"y":20,"w":33,"h":37},
	"sourceSize": {"w":69,"h":87},
	"pivot": {"x":0.5,"y":0.5}
},
"Buzzar/Hurt0000":
{
	"frame": {"x":404,"y":1081,"w":33,"h":34},
	"rotated": false,
	"trimmed": true,
	"spriteSourceSize": {"x":13,"y":27,"w":33,"h":34},
	"sourceSize": {"w":69,"h":87},
	"pivot": {"x":0.5,"y":0.5}
},
"Buzzar/Hurt0001":
{
	"frame": {"x":370,"y":1113,"w":33,"h":34},
	"rotated": false,
	"trimmed": true,
	"spriteSourceSize": {"x":13,"y":28,"w":33,"h":34},
	"sourceSize": {"w":69,"h":87},
	"pivot": {"x":0.5,"y":0.5}
},
"Buzzar/Idle0000":
{
	"frame": {"x":308,"y":1081,"w":32,"h":41},
	"rotated": false,
	"trimmed": true,
	"spriteSourceSize": {"x":18,"y":20,"w":32,"h":41},
	"sourceSize": {"w":69,"h":87},
	"pivot": {"x":0.5,"y":0.5}
},
"Buzzar/Idle0001":
{
	"frame": {"x":320,"y":1005,"w":32,"h":41},
	"rotated": false,
	"trimmed": true,
	"spriteSourceSize": {"x":18,"y":20,"w":32,"h":41},
	"sourceSize": {"w":69,"h":87},
	"pivot": {"x":0.5,"y":0.5}
},
"CreeperThistle/CreeperThistle0000":
{
	"frame": {"x":346,"y":963,"w":39,"h":32},
	"rotated": false,
	"trimmed": true,
	"spriteSourceSize": {"x":3,"y":2,"w":39,"h":32},
	"sourceSize": {"w":44,"h":37},
	"pivot": {"x":0.5,"y":0.5}
},
"CreeperThistle/CreeperThistle0001":
{
	"frame": {"x":289,"y":1049,"w":39,"h":31},
	"rotated": false,
	"trimmed": true,
	"spriteSourceSize": {"x":3,"y":3,"w":39,"h":31},
	"sourceSize": {"w":44,"h":37},
	"pivot": {"x":0.5,"y":0.5}
},
"CreeperThistle/CreeperThistle0002":
{
	"frame": {"x":369,"y":1042,"w":39,"h":32},
	"rotated": false,
	"trimmed": true,
	"spriteSourceSize": {"x":3,"y":2,"w":39,"h":32},
	"sourceSize": {"w":44,"h":37},
	"pivot": {"x":0.5,"y":0.5}
},
"CreeperThistle/CreeperThistle0003":
{
	"frame": {"x":329,"y":1047,"w":39,"h":33},
	"rotated": false,
	"trimmed": true,
	"spriteSourceSize": {"x":3,"y":1,"w":39,"h":33},
	"sourceSize": {"w":44,"h":37},
	"pivot": {"x":0.5,"y":0.5}
},
"Fungu/Fungu0000":
{
	"frame": {"x":420,"y":483,"w":32,"h":61},
	"rotated": false,
	"trimmed": true,
	"spriteSourceSize": {"x":18,"y":4,"w":32,"h":61},
	"sourceSize": {"w":70,"h":70},
	"pivot": {"x":0.5,"y":0.5}
},
"Fungu/Fungu0001":
{
	"frame": {"x":453,"y":535,"w":32,"h":61},
	"rotated": false,
	"trimmed": true,
	"spriteSourceSize": {"x":18,"y":4,"w":32,"h":61},
	"sourceSize": {"w":70,"h":70},
	"pivot": {"x":0.5,"y":0.5}
},
"Goddess/Goddess0000":
{
	"frame": {"x":1,"y":595,"w":98,"h":125},
	"rotated": false,
	"trimmed": true,
	"spriteSourceSize": {"x":25,"y":20,"w":98,"h":125},
	"sourceSize": {"w":143,"h":164},
	"pivot": {"x":0.5,"y":0.5}
},
"GUBr/Attack0000":
{
	"frame": {"x":282,"y":341,"w":59,"h":54},
	"rotated": false,
	"trimmed": true,
	"spriteSourceSize": {"x":74,"y":75,"w":59,"h":54},
	"sourceSize": {"w":200,"h":200},
	"pivot": {"x":0.5,"y":0.5}
},
"GUBr/Attack0001":
{
	"frame": {"x":123,"y":529,"w":60,"h":65},
	"rotated": false,
	"trimmed": true,
	"spriteSourceSize": {"x":68,"y":64,"w":60,"h":65},
	"sourceSize": {"w":200,"h":200},
	"pivot": {"x":0.5,"y":0.5}
},
"GUBr/Attack0002":
{
	"frame": {"x":386,"y":870,"w":58,"h":49},
	"rotated": false,
	"trimmed": true,
	"spriteSourceSize": {"x":63,"y":80,"w":58,"h":49},
	"sourceSize": {"w":200,"h":200},
	"pivot": {"x":0.5,"y":0.5}
},
"GUBr/Attack0003":
{
	"frame": {"x":108,"y":886,"w":96,"h":47},
	"rotated": false,
	"trimmed": true,
	"spriteSourceSize": {"x":74,"y":82,"w":96,"h":47},
	"sourceSize": {"w":200,"h":200},
	"pivot": {"x":0.5,"y":0.5}
},
"GUBr/Attack0004":
{
	"frame": {"x":289,"y":216,"w":78,"h":49},
	"rotated": false,
	"trimmed": true,
	"spriteSourceSize": {"x":79,"y":80,"w":78,"h":49},
	"sourceSize": {"w":200,"h":200},
	"pivot": {"x":0.5,"y":0.5}
},
"GUBr/Attack0005":
{
	"frame": {"x":238,"y":883,"w":56,"h":50},
	"rotated": false,
	"trimmed": true,
	"spriteSourceSize": {"x":77,"y":79,"w":56,"h":50},
	"sourceSize": {"w":200,"h":200},
	"pivot": {"x":0.5,"y":0.5}
},
"GUBr/Cower0000":
{
	"frame": {"x":449,"y":159,"w":36,"h":62},
	"rotated": false,
	"trimmed": true,
	"spriteSourceSize": {"x":83,"y":67,"w":36,"h":62},
	"sourceSize": {"w":200,"h":200},
	"pivot": {"x":0.5,"y":0.5}
},
"GUBr/Cower0001":
{
	"frame": {"x":450,"y":607,"w":38,"h":63},
	"rotated": false,
	"trimmed": true,
	"spriteSourceSize": {"x":83,"y":66,"w":38,"h":63},
	"sourceSize": {"w":200,"h":200},
	"pivot": {"x":0.5,"y":0.5}
},
"GUBr/Cower0002":
{
	"frame": {"x":453,"y":470,"w":36,"h":64},
	"rotated": false,
	"trimmed": true,
	"spriteSourceSize": {"x":83,"y":65,"w":36,"h":64},
	"sourceSize": {"w":200,"h":200},
	"pivot": {"x":0.5,"y":0.5}
},
"GUBr/Cower0003":
{
	"frame": {"x":301,"y":821,"w":38,"h":62},
	"rotated": false,
	"trimmed": true,
	"spriteSourceSize": {"x":83,"y":67,"w":38,"h":62},
	"sourceSize": {"w":200,"h":200},
	"pivot": {"x":0.5,"y":0.5}
},
"GUBr/Hit0000":
{
	"frame": {"x":264,"y":396,"w":58,"h":63},
	"rotated": false,
	"trimmed": true,
	"spriteSourceSize": {"x":77,"y":66,"w":58,"h":63},
	"sourceSize": {"w":200,"h":200},
	"pivot": {"x":0.5,"y":0.5}
},
"GUBr/Stand0000":
{
	"frame": {"x":248,"y":934,"w":48,"h":58},
	"rotated": false,
	"trimmed": true,
	"spriteSourceSize": {"x":79,"y":71,"w":48,"h":58},
	"sourceSize": {"w":200,"h":200},
	"pivot": {"x":0.5,"y":0.5}
},
"GUBr/Walk0000":
{
	"frame": {"x":445,"y":800,"w":45,"h":59},
	"rotated": false,
	"trimmed": true,
	"spriteSourceSize": {"x":78,"y":65,"w":45,"h":59},
	"sourceSize": {"w":200,"h":200},
	"pivot": {"x":0.5,"y":0.5}
},
"GUBr/Walk0001":
{
	"frame": {"x":413,"y":545,"w":39,"h":61},
	"rotated": false,
	"trimmed": true,
	"spriteSourceSize": {"x":81,"y":68,"w":39,"h":61},
	"sourceSize": {"w":200,"h":200},
	"pivot": {"x":0.5,"y":0.5}
},
"GUBr/Walk0002":
{
	"frame": {"x":445,"y":860,"w":45,"h":59},
	"rotated": false,
	"trimmed": true,
	"spriteSourceSize": {"x":78,"y":66,"w":45,"h":59},
	"sourceSize": {"w":200,"h":200},
	"pivot": {"x":0.5,"y":0.5}
},
"GUBr/Walk0003":
{
	"frame": {"x":340,"y":814,"w":45,"h":62},
	"rotated": false,
	"trimmed": true,
	"spriteSourceSize": {"x":78,"y":67,"w":45,"h":62},
	"sourceSize": {"w":200,"h":200},
	"pivot": {"x":0.5,"y":0.5}
},
"Haystax/Idle0000":
{
	"frame": {"x":100,"y":595,"w":67,"h":84},
	"rotated": false,
	"trimmed": true,
	"spriteSourceSize": {"x":17,"y":10,"w":67,"h":84},
	"sourceSize": {"w":100,"h":100},
	"pivot": {"x":0.5,"y":0.5}
},
"Haystax/Idle0001":
{
	"frame": {"x":162,"y":264,"w":64,"h":80},
	"rotated": false,
	"trimmed": true,
	"spriteSourceSize": {"x":17,"y":14,"w":64,"h":80},
	"sourceSize": {"w":100,"h":100},
	"pivot": {"x":0.5,"y":0.5}
},
"Haystax/Tarball0000":
{
	"frame": {"x":349,"y":1123,"w":20,"h":23},
	"rotated": false,
	"trimmed": true,
	"spriteSourceSize": {"x":0,"y":0,"w":20,"h":23},
	"sourceSize": {"w":21,"h":23},
	"pivot": {"x":0.5,"y":0.5}
},
"Haystax/Tarball0001":
{
	"frame": {"x":438,"y":1081,"w":21,"h":20},
	"rotated": false,
	"trimmed": true,
	"spriteSourceSize": {"x":0,"y":1,"w":21,"h":20},
	"sourceSize": {"w":21,"h":23},
	"pivot": {"x":0.5,"y":0.5}
},
"HWK9/AttackDash0000":
{
	"frame": {"x":1,"y":933,"w":99,"h":78},
	"rotated": false,
	"trimmed": true,
	"spriteSourceSize": {"x":34,"y":59,"w":99,"h":78},
	"sourceSize": {"w":200,"h":200},
	"pivot": {"x":0.5,"y":0.5}
},
"HWK9/AttackDash0001":
{
	"frame": {"x":1,"y":364,"w":123,"h":117},
	"rotated": false,
	"trimmed": true,
	"spriteSourceSize": {"x":47,"y":37,"w":123,"h":117},
	"sourceSize": {"w":200,"h":200},
	"pivot": {"x":0.5,"y":0.5}
},
"HWK9/AttackDash0002":
{
	"frame": {"x":181,"y":1,"w":108,"h":105},
	"rotated": false,
	"trimmed": true,
	"spriteSourceSize": {"x":58,"y":25,"w":108,"h":105},
	"sourceSize": {"w":200,"h":200},
	"pivot": {"x":0.5,"y":0.5}
},
"HWK9/AttackDash0003":
{
	"frame": {"x":290,"y":1,"w":104,"h":106},
	"rotated": false,
	"trimmed": true,
	"spriteSourceSize": {"x":56,"y":21,"w":104,"h":106},
	"sourceSize": {"w":200,"h":200},
	"pivot": {"x":0.5,"y":0.5}
},
"HWK9/Block0000":
{
	"frame": {"x":395,"y":1,"w":93,"h":82},
	"rotated": false,
	"trimmed": true,
	"spriteSourceSize": {"x":36,"y":54,"w":93,"h":82},
	"sourceSize": {"w":200,"h":200},
	"pivot": {"x":0.5,"y":0.5}
},
"HWK9/Flip0000":
{
	"frame": {"x":295,"y":884,"w":32,"h":49},
	"rotated": false,
	"trimmed": true,
	"spriteSourceSize": {"x":85,"y":73,"w":32,"h":49},
	"sourceSize": {"w":200,"h":200},
	"pivot": {"x":0.5,"y":0.5}
},
"HWK9/Flip0001":
{
	"frame": {"x":450,"y":222,"w":40,"h":40},
	"rotated": false,
	"trimmed": true,
	"spriteSourceSize": {"x":81,"y":80,"w":40,"h":40},
	"sourceSize": {"w":200,"h":200},
	"pivot": {"x":0.5,"y":0.5}
},
"HWK9/Flip0002":
{
	"frame": {"x":386,"y":920,"w":48,"h":34},
	"rotated": false,
	"trimmed": true,
	"spriteSourceSize": {"x":79,"y":84,"w":48,"h":34},
	"sourceSize": {"w":200,"h":200},
	"pivot": {"x":0.5,"y":0.5}
},
"HWK9/Flip0003":
{
	"frame": {"x":421,"y":955,"w":32,"h":49},
	"rotated": false,
	"trimmed": true,
	"spriteSourceSize": {"x":83,"y":78,"w":32,"h":49},
	"sourceSize": {"w":200,"h":200},
	"pivot": {"x":0.5,"y":0.5}
},
"HWK9/Flip0004":
{
	"frame": {"x":450,"y":263,"w":40,"h":40},
	"rotated": false,
	"trimmed": true,
	"spriteSourceSize": {"x":80,"y":81,"w":40,"h":40},
	"sourceSize": {"w":200,"h":200},
	"pivot": {"x":0.5,"y":0.5}
},
"HWK9/Flip0005":
{
	"frame": {"x":435,"y":920,"w":48,"h":34},
	"rotated": false,
	"trimmed": true,
	"spriteSourceSize": {"x":74,"y":83,"w":48,"h":34},
	"sourceSize": {"w":200,"h":200},
	"pivot": {"x":0.5,"y":0.5}
},
"HWK9/Stand0000":
{
	"frame": {"x":455,"y":331,"w":32,"h":56},
	"rotated": false,
	"trimmed": true,
	"spriteSourceSize": {"x":83,"y":74,"w":32,"h":56},
	"sourceSize": {"w":200,"h":200},
	"pivot": {"x":0.5,"y":0.5}
},
"Insectoid/Die0000":
{
	"frame": {"x":399,"y":607,"w":50,"h":63},
	"rotated": false,
	"trimmed": true,
	"spriteSourceSize": {"x":76,"y":70,"w":50,"h":63},
	"sourceSize": {"w":200,"h":200},
	"pivot": {"x":0.5,"y":0.5}
},
"Insectoid/Hop0000":
{
	"frame": {"x":368,"y":222,"w":76,"h":36},
	"rotated": false,
	"trimmed": true,
	"spriteSourceSize": {"x":14,"y":45,"w":76,"h":36},
	"sourceSize": {"w":100,"h":100},
	"pivot": {"x":0.5,"y":0.5}
},
"Insectoid/Hop0001":
{
	"frame": {"x":192,"y":345,"w":84,"h":50},
	"rotated": false,
	"trimmed": true,
	"spriteSourceSize": {"x":8,"y":41,"w":84,"h":50},
	"sourceSize": {"w":100,"h":100},
	"pivot": {"x":0.5,"y":0.5}
},
"Insectoid/Hop0002":
{
	"frame": {"x":290,"y":171,"w":88,"h":44},
	"rotated": false,
	"trimmed": true,
	"spriteSourceSize": {"x":8,"y":39,"w":88,"h":44},
	"sourceSize": {"w":100,"h":100},
	"pivot": {"x":0.5,"y":0.5}
},
"Insectoid/Spin0000":
{
	"frame": {"x":297,"y":934,"w":48,"h":56},
	"rotated": false,
	"trimmed": true,
	"spriteSourceSize": {"x":79,"y":73,"w":48,"h":56},
	"sourceSize": {"w":200,"h":200},
	"pivot": {"x":0.5,"y":0.5}
},
"KR32/Attack0000":
{
	"frame": {"x":433,"y":736,"w":49,"h":63},
	"rotated": false,
	"trimmed": true,
	"spriteSourceSize": {"x":101,"y":66,"w":49,"h":63},
	"sourceSize": {"w":240,"h":200},
	"pivot": {"x":0.5,"y":0.5}
},
"KR32/Attack0001":
{
	"frame": {"x":1,"y":1081,"w":67,"h":71},
	"rotated": false,
	"trimmed": true,
	"spriteSourceSize": {"x":99,"y":58,"w":67,"h":71},
	"sourceSize": {"w":240,"h":200},
	"pivot": {"x":0.5,"y":0.5}
},
"KR32/Attack0002":
{
	"frame": {"x":1,"y":721,"w":93,"h":112},
	"rotated": false,
	"trimmed": true,
	"spriteSourceSize": {"x":75,"y":17,"w":93,"h":112},
	"sourceSize": {"w":240,"h":200},
	"pivot": {"x":0.5,"y":0.5}
},
"KR32/Attack0003":
{
	"frame": {"x":1,"y":482,"w":121,"h":112},
	"rotated": false,
	"trimmed": true,
	"spriteSourceSize": {"x":42,"y":17,"w":121,"h":112},
	"sourceSize": {"w":240,"h":200},
	"pivot": {"x":0.5,"y":0.5}
},
"KR32/Attack0004":
{
	"frame": {"x":1,"y":834,"w":106,"h":98},
	"rotated": false,
	"trimmed": true,
	"spriteSourceSize": {"x":39,"y":31,"w":106,"h":98},
	"sourceSize": {"w":240,"h":200},
	"pivot": {"x":0.5,"y":0.5}
},
"KR32/Attack0005":
{
	"frame": {"x":1,"y":1,"w":179,"h":110},
	"rotated": false,
	"trimmed": true,
	"spriteSourceSize": {"x":51,"y":19,"w":179,"h":110},
	"sourceSize": {"w":240,"h":200},
	"pivot": {"x":0.5,"y":0.5}
},
"KR32/Attack0006":
{
	"frame": {"x":1,"y":112,"w":166,"h":123},
	"rotated": false,
	"trimmed": true,
	"spriteSourceSize": {"x":64,"y":6,"w":166,"h":123},
	"sourceSize": {"w":240,"h":200},
	"pivot": {"x":0.5,"y":0.5}
},
"KR32/Attack0007":
{
	"frame": {"x":1,"y":236,"w":160,"h":127},
	"rotated": false,
	"trimmed": true,
	"spriteSourceSize": {"x":69,"y":2,"w":160,"h":127},
	"sourceSize": {"w":240,"h":200},
	"pivot": {"x":0.5,"y":0.5}
},
"KR32/Attack0008":
{
	"frame": {"x":108,"y":820,"w":129,"h":65},
	"rotated": false,
	"trimmed": true,
	"spriteSourceSize": {"x":100,"y":64,"w":129,"h":65},
	"sourceSize": {"w":240,"h":200},
	"pivot": {"x":0.5,"y":0.5}
},
"KR32/Block0000":
{
	"frame": {"x":314,"y":675,"w":49,"h":70},
	"rotated": false,
	"trimmed": true,
	"spriteSourceSize": {"x":80,"y":59,"w":49,"h":70},
	"sourceSize": {"w":200,"h":200},
	"pivot": {"x":0.5,"y":0.5}
},
"KR32/Block0001":
{
	"frame": {"x":69,"y":1081,"w":67,"h":71},
	"rotated": false,
	"trimmed": true,
	"spriteSourceSize": {"x":78,"y":58,"w":67,"h":71},
	"sourceSize": {"w":200,"h":200},
	"pivot": {"x":0.5,"y":0.5}
},
"KR32/Block0002":
{
	"frame": {"x":125,"y":364,"w":66,"h":94},
	"rotated": false,
	"trimmed": true,
	"spriteSourceSize": {"x":82,"y":35,"w":66,"h":94},
	"sourceSize": {"w":200,"h":200},
	"pivot": {"x":0.5,"y":0.5}
},
"KR32/Block0003":
{
	"frame": {"x":231,"y":186,"w":57,"h":77},
	"rotated": false,
	"trimmed": true,
	"spriteSourceSize": {"x":81,"y":52,"w":57,"h":77},
	"sourceSize": {"w":200,"h":200},
	"pivot": {"x":0.5,"y":0.5}
},
"KR32/Block0004":
{
	"frame": {"x":230,"y":1004,"w":58,"h":76},
	"rotated": false,
	"trimmed": true,
	"spriteSourceSize": {"x":81,"y":53,"w":58,"h":76},
	"sourceSize": {"w":200,"h":200},
	"pivot": {"x":0.5,"y":0.5}
},
"KR32/Block0005":
{
	"frame": {"x":257,"y":676,"w":56,"h":76},
	"rotated": false,
	"trimmed": true,
	"spriteSourceSize": {"x":81,"y":53,"w":56,"h":76},
	"sourceSize": {"w":200,"h":200},
	"pivot": {"x":0.5,"y":0.5}
},
"KR32/Hit0000":
{
	"frame": {"x":238,"y":821,"w":62,"h":61},
	"rotated": false,
	"trimmed": true,
	"spriteSourceSize": {"x":66,"y":68,"w":62,"h":61},
	"sourceSize": {"w":200,"h":200},
	"pivot": {"x":0.5,"y":0.5}
},
"KR32/Jump0000":
{
	"frame": {"x":386,"y":809,"w":58,"h":60},
	"rotated": false,
	"trimmed": true,
	"spriteSourceSize": {"x":68,"y":69,"w":58,"h":60},
	"sourceSize": {"w":200,"h":200},
	"pivot": {"x":0.5,"y":0.5}
},
"KR32/Jump0001":
{
	"frame": {"x":192,"y":396,"w":71,"h":63},
	"rotated": false,
	"trimmed": true,
	"spriteSourceSize": {"x":72,"y":65,"w":71,"h":63},
	"sourceSize": {"w":200,"h":200},
	"pivot": {"x":0.5,"y":0.5}
},
"KR32/Jump0002":
{
	"frame": {"x":323,"y":419,"w":60,"h":63},
	"rotated": false,
	"trimmed": true,
	"spriteSourceSize": {"x":83,"y":64,"w":60,"h":63},
	"sourceSize": {"w":200,"h":200},
	"pivot": {"x":0.5,"y":0.5}
},
"KR32/Jump0003":
{
	"frame": {"x":323,"y":419,"w":60,"h":63},
	"rotated": false,
	"trimmed": true,
	"spriteSourceSize": {"x":83,"y":65,"w":60,"h":63},
	"sourceSize": {"w":200,"h":200},
	"pivot": {"x":0.5,"y":0.5}
},
"KR32/Jump0004":
{
	"frame": {"x":360,"y":483,"w":59,"h":60},
	"rotated": false,
	"trimmed": true,
	"spriteSourceSize": {"x":76,"y":69,"w":59,"h":60},
	"sourceSize": {"w":200,"h":200},
	"pivot": {"x":0.5,"y":0.5}
},
"KR32/Jump0005":
{
	"frame": {"x":384,"y":421,"w":59,"h":61},
	"rotated": false,
	"trimmed": true,
	"spriteSourceSize": {"x":63,"y":65,"w":59,"h":61},
	"sourceSize": {"w":200,"h":200},
	"pivot": {"x":0.5,"y":0.5}
},
"KR32/Jump0006":
{
	"frame": {"x":353,"y":544,"w":59,"h":61},
	"rotated": false,
	"trimmed": true,
	"spriteSourceSize": {"x":63,"y":64,"w":59,"h":61},
	"sourceSize": {"w":200,"h":200},
	"pivot": {"x":0.5,"y":0.5}
},
"KR32/Jump0007":
{
	"frame": {"x":353,"y":544,"w":59,"h":61},
	"rotated": false,
	"trimmed": true,
	"spriteSourceSize": {"x":63,"y":65,"w":59,"h":61},
	"sourceSize": {"w":200,"h":200},
	"pivot": {"x":0.5,"y":0.5}
},
"KR32/Stab0000":
{
	"frame": {"x":424,"y":671,"w":49,"h":64},
	"rotated": false,
	"trimmed": true,
	"spriteSourceSize": {"x":81,"y":65,"w":49,"h":64},
	"sourceSize": {"w":200,"h":200},
	"pivot": {"x":0.5,"y":0.5}
},
"KR32/Stab0001":
{
	"frame": {"x":290,"y":108,"w":84,"h":62},
	"rotated": false,
	"trimmed": true,
	"spriteSourceSize": {"x":82,"y":67,"w":84,"h":62},
	"sourceSize": {"w":200,"h":200},
	"pivot": {"x":0.5,"y":0.5}
},
"KR32/Stab0002":
{
	"frame": {"x":379,"y":159,"w":69,"h":62},
	"rotated": false,
	"trimmed": true,
	"spriteSourceSize": {"x":82,"y":67,"w":69,"h":62},
	"sourceSize": {"w":200,"h":200},
	"pivot": {"x":0.5,"y":0.5}
},
"KR32/Stand0000":
{
	"frame": {"x":339,"y":606,"w":59,"h":67},
	"rotated": false,
	"trimmed": true,
	"spriteSourceSize": {"x":71,"y":62,"w":59,"h":67},
	"sourceSize": {"w":200,"h":200},
	"pivot": {"x":0.5,"y":0.5}
},
"KR32/Stand0001":
{
	"frame": {"x":364,"y":674,"w":59,"h":67},
	"rotated": false,
	"trimmed": true,
	"spriteSourceSize": {"x":71,"y":62,"w":59,"h":67},
	"sourceSize": {"w":200,"h":200},
	"pivot": {"x":0.5,"y":0.5}
},
"KR32/Stand0002":
{
	"frame": {"x":373,"y":742,"w":59,"h":66},
	"rotated": false,
	"trimmed": true,
	"spriteSourceSize": {"x":71,"y":63,"w":59,"h":66},
	"sourceSize": {"w":200,"h":200},
	"pivot": {"x":0.5,"y":0.5}
},
"KR32/WalkBack0000":
{
	"frame": {"x":109,"y":1004,"w":60,"h":76},
	"rotated": false,
	"trimmed": true,
	"spriteSourceSize": {"x":78,"y":53,"w":60,"h":76},
	"sourceSize": {"w":200,"h":200},
	"pivot": {"x":0.5,"y":0.5}
},
"KR32/WalkBack0001":
{
	"frame": {"x":282,"y":598,"w":56,"h":76},
	"rotated": false,
	"trimmed": true,
	"spriteSourceSize": {"x":76,"y":53,"w":56,"h":76},
	"sourceSize": {"w":200,"h":200},
	"pivot": {"x":0.5,"y":0.5}
},
"KR32/WalkBack0002":
{
	"frame": {"x":168,"y":598,"w":56,"h":77},
	"rotated": false,
	"trimmed": true,
	"spriteSourceSize": {"x":77,"y":52,"w":56,"h":77},
	"sourceSize": {"w":200,"h":200},
	"pivot": {"x":0.5,"y":0.5}
},
"KR32/WalkBack0003":
{
	"frame": {"x":225,"y":598,"w":56,"h":77},
	"rotated": false,
	"trimmed": true,
	"spriteSourceSize": {"x":81,"y":52,"w":56,"h":77},
	"sourceSize": {"w":200,"h":200},
	"pivot": {"x":0.5,"y":0.5}
},
"KR32/WalkFront0000":
{
	"frame": {"x":227,"y":264,"w":54,"h":80},
	"rotated": false,
	"trimmed": true,
	"spriteSourceSize": {"x":81,"y":49,"w":54,"h":80},
	"sourceSize": {"w":200,"h":200},
	"pivot": {"x":0.5,"y":0.5}
},
"KR32/WalkFront0001":
{
	"frame": {"x":168,"y":112,"w":57,"h":81},
	"rotated": false,
	"trimmed": true,
	"spriteSourceSize": {"x":81,"y":48,"w":57,"h":81},
	"sourceSize": {"w":200,"h":200},
	"pivot": {"x":0.5,"y":0.5}
},
"KR32/WalkFront0002":
{
	"frame": {"x":397,"y":259,"w":52,"h":80},
	"rotated": false,
	"trimmed": true,
	"spriteSourceSize": {"x":84,"y":49,"w":52,"h":80},
	"sourceSize": {"w":200,"h":200},
	"pivot": {"x":0.5,"y":0.5}
},
"KR32/WalkFront0003":
{
	"frame": {"x":402,"y":340,"w":52,"h":80},
	"rotated": false,
	"trimmed": true,
	"spriteSourceSize": {"x":81,"y":49,"w":52,"h":80},
	"sourceSize": {"w":200,"h":200},
	"pivot": {"x":0.5,"y":0.5}
},
"Mask/Mask0000":
{
	"frame": {"x":386,"y":955,"w":34,"h":48},
	"rotated": false,
	"trimmed": true,
	"spriteSourceSize": {"x":10,"y":5,"w":34,"h":48},
	"sourceSize": {"w":60,"h":60},
	"pivot": {"x":0.5,"y":0.5}
},
"R2BTU/Attack0000":
{
	"frame": {"x":340,"y":877,"w":45,"h":41},
	"rotated": false,
	"trimmed": true,
	"spriteSourceSize": {"x":137,"y":123,"w":45,"h":41},
	"sourceSize": {"w":300,"h":300},
	"pivot": {"x":0.5,"y":0.5}
},
"R2BTU/Attack0001":
{
	"frame": {"x":346,"y":919,"w":39,"h":43},
	"rotated": false,
	"trimmed": true,
	"spriteSourceSize": {"x":137,"y":121,"w":39,"h":43},
	"sourceSize": {"w":300,"h":300},
	"pivot": {"x":0.5,"y":0.5}
},
"R2BTU/Attack0002":
{
	"frame": {"x":444,"y":421,"w":46,"h":48},
	"rotated": false,
	"trimmed": true,
	"spriteSourceSize": {"x":137,"y":123,"w":46,"h":48},
	"sourceSize": {"w":300,"h":300},
	"pivot": {"x":0.5,"y":0.5}
},
"R2BTU/Attack0003":
{
	"frame": {"x":312,"y":483,"w":47,"h":46},
	"rotated": false,
	"trimmed": true,
	"spriteSourceSize": {"x":137,"y":123,"w":47,"h":46},
	"sourceSize": {"w":300,"h":300},
	"pivot": {"x":0.5,"y":0.5}
},
"R2BTU/Float0000":
{
	"frame": {"x":289,"y":1005,"w":30,"h":43},
	"rotated": false,
	"trimmed": true,
	"spriteSourceSize": {"x":136,"y":124,"w":30,"h":43},
	"sourceSize": {"w":300,"h":300},
	"pivot": {"x":0.5,"y":0.5}
},
"R2BTU/Float0001":
{
	"frame": {"x":353,"y":996,"w":30,"h":40},
	"rotated": false,
	"trimmed": true,
	"spriteSourceSize": {"x":136,"y":123,"w":30,"h":40},
	"sourceSize": {"w":300,"h":300},
	"pivot": {"x":0.5,"y":0.5}
},
"R2BTU/Stand0000":
{
	"frame": {"x":341,"y":1081,"w":28,"h":41},
	"rotated": false,
	"trimmed": true,
	"spriteSourceSize": {"x":137,"y":124,"w":28,"h":41},
	"sourceSize": {"w":300,"h":300},
	"pivot": {"x":0.5,"y":0.5}
},
"Sporoid/Spore0000":
{
	"frame": {"x":328,"y":919,"w":14,"h":14},
	"rotated": false,
	"trimmed": true,
	"spriteSourceSize": {"x":3,"y":2,"w":14,"h":14},
	"sourceSize": {"w":20,"h":20},
	"pivot": {"x":0.5,"y":0.5}
},
"Sporoid/Spore0001":
{
	"frame": {"x":162,"y":345,"w":14,"h":14},
	"rotated": false,
	"trimmed": true,
	"spriteSourceSize": {"x":3,"y":2,"w":14,"h":14},
	"sourceSize": {"w":20,"h":20},
	"pivot": {"x":0.5,"y":0.5}
},
"Sporoid/Sporoid0000":
{
	"frame": {"x":452,"y":1005,"w":38,"h":24},
	"rotated": false,
	"trimmed": true,
	"spriteSourceSize": {"x":30,"y":42,"w":38,"h":24},
	"sourceSize": {"w":100,"h":100},
	"pivot": {"x":0.5,"y":0.5}
},
"Sporoid/Sporoid0001":
{
	"frame": {"x":443,"y":1055,"w":39,"h":24},
	"rotated": false,
	"trimmed": true,
	"spriteSourceSize": {"x":30,"y":41,"w":39,"h":24},
	"sourceSize": {"w":100,"h":100},
	"pivot": {"x":0.5,"y":0.5}
},
"Sporoid/Sporoid0002":
{
	"frame": {"x":450,"y":304,"w":40,"h":26},
	"rotated": false,
	"trimmed": true,
	"spriteSourceSize": {"x":30,"y":40,"w":40,"h":26},
	"sourceSize": {"w":100,"h":100},
	"pivot": {"x":0.5,"y":0.5}
},
"Sporoid/Sporoid0003":
{
	"frame": {"x":308,"y":1123,"w":40,"h":26},
	"rotated": false,
	"trimmed": true,
	"spriteSourceSize": {"x":29,"y":41,"w":40,"h":26},
	"sourceSize": {"w":100,"h":100},
	"pivot": {"x":0.5,"y":0.5}
},
"Sporoid/Sporoid0004":
{
	"frame": {"x":404,"y":1116,"w":39,"h":23},
	"rotated": false,
	"trimmed": true,
	"spriteSourceSize": {"x":29,"y":42,"w":39,"h":23},
	"sourceSize": {"w":100,"h":100},
	"pivot": {"x":0.5,"y":0.5}
},
"Sporoid/Sporoid0005":
{
	"frame": {"x":452,"y":1030,"w":37,"h":24},
	"rotated": false,
	"trimmed": true,
	"spriteSourceSize": {"x":30,"y":43,"w":37,"h":24},
	"sourceSize": {"w":100,"h":100},
	"pivot": {"x":0.5,"y":0.5}
}},
"meta": {
	"app": "http://www.codeandweb.com/texturepacker",
	"version": "1.0",
	"image": "Enemies.png",
	"format": "RGBA8888",
	"size": {"w":491,"h":1153},
	"scale": "1",
	"smartupdate": "$TexturePacker:SmartUpdate:7d405a2dde57c403e81afd44a92028ac:f4124f77d5f6f3bc280e2f3ba3f01286:b1585ba32d60cf5440f3fdffe8c37c76$"
}
}
